<xml xmlns="https://developers.google.com/blockly/xml"><variables><variable id="LF~^7y/5DU3P0YQE#o=}">inputField</variable></variables><block type="variables_def" id="*DkxMxGfmB),A:eJP^*g" x="-1" y="-72"><mutation xmlns="http://www.w3.org/1999/xhtml" no_input="false" variable_uuid="24b66df5-ff5e-4123-b871-0e48b7557760" variable_name="canMove" variable_scope="APP"/><field name="SCOPE">APP</field><field name="NAME">canMove</field><value name="VALUE"><block type="logic_boolean" id="TC`XxAv`Au-2R/_zS3wt"><field name="BOOL">TRUE</field></block></value></block><block type="component_event" id="QpWeY.Q99Nb=dlBb5Qy*" x="0" y="0"><mutation xmlns="http://www.w3.org/1999/xhtml" component_name="logoutButton" component_type="Label" parent_id="undefined" event_id="Click" was_updated="true"/><field name="component_id">93d5f47f-5e0b-42aa-9d33-ba100e0b8b49</field><field name="event_id">Click</field><comment pinned="false" h="80" w="160">When logoutButton is clicked, log out the user</comment><statement name="input_do"><block type="signin_sign_out_advanced" id="]VlSKV}p`_$tb+MBQb;w" inline="false"><mutation xmlns="http://www.w3.org/1999/xhtml" show_callback_params="true" callback_params_added="true"/><value name="CALLBACK_PARAM0"><block type="callback_arg" id="GD4?q?K@LUTnQ,#R9L{^"><mutation xmlns="http://www.w3.org/1999/xhtml" tooltip="" language_neutral_name="error" arg_name_trans_key="blocks.signin.error" old_arg_name="error"/></block></value><statement name="DO"><block type="controls_if" id="MO2U.qwF-voru_0);;DE"><mutation else="1"/><value name="IF0"><block type="callback_arg" id="064uLs!1MK+[z8YVo0m3"><mutation xmlns="http://www.w3.org/1999/xhtml" tooltip="" language_neutral_name="error" arg_name_trans_key="blocks.signin.error" old_arg_name="error" is_detached_parameter="true"/></block></value><statement name="DO0"><block type="setter" id="yhO-KPDepG/v0tL7xa2B"><mutation xmlns="http://www.w3.org/1999/xhtml" component_name="error_label(Profile)" parent_id="undefined"/><field name="component_id">c06550f1-e444-496b-b03f-e4ddbc3a4147</field><field name="field_name">Text</field><value name="field_value"><shadow type="text" id="B*JOjCFW@)4yHP*+PVNP"><field name="TEXT">Label</field></shadow><block type="callback_arg" id=".JDVF#I-2|S]Fu8`e^FK"><mutation xmlns="http://www.w3.org/1999/xhtml" tooltip="" language_neutral_name="error" arg_name_trans_key="blocks.signin.error" old_arg_name="error" is_detached_parameter="true"/></block></value></block></statement><statement name="ELSE"><block type="controls_navigate_new" id="u]Y4P=)Eq0tLrMutt}=Q"><value name="COMPONENT"><shadow type="any_component_component_dropdown" id="#s1-vz6Po~wzMK7hF2OR"><mutation xmlns="http://www.w3.org/1999/xhtml" component_id="Login" component_types_to_include="[&quot;Screen&quot;]"/><field name="component_id">51f75d1c-6a4d-4a50-a3c0-9e35bcb415c2</field></shadow></value></block></statement></block></statement></block></statement></block><block type="procedures_defnoreturn" id="/L`#UX(%=0cflj~{hZ2j" x="892" y="-13"><mutation><arg name="inputField" varid="LF~^7y/5DU3P0YQE#o=}"/></mutation><field name="NAME">updateUserData</field><comment pinned="false" h="80" w="160">Describe this function...</comment><statement name="STACK"><block type="controls_if" id="0*voI}5r:q2HCFnW1zsa"><mutation else="1"/><value name="IF0"><block type="text_isEmpty" id="P4SO:DB.7(WG~do|A~Q8"><value name="VALUE"><shadow type="text" id="%9dYy~Mwz!vrJ_WyNwMh"><field name="TEXT"/></shadow><block type="set_get" id="-:83i,ZpMc-XGL?9r(Ax"><mutation xmlns="http://www.w3.org/1999/xhtml" component_block_input="true"/><field name="TYPE_component_id">Label</field><field name="field_name">Text</field><value name="component_id_SOCKET"><shadow type="any_component_component_dropdown" id="IjHuV!2+_0`L:I*psC%z"><mutation xmlns="http://www.w3.org/1999/xhtml" component_id="error_label(Profile)" include_has_gettable_only="true"/><field name="component_id">c06550f1-e444-496b-b03f-e4ddbc3a4147</field></shadow><block type="text_join" id="D2.r(g|T+y9]p]i:t3oX"><mutation items="2"/><value name="ADD0"><block type="variables_get" id="{/7%FoQ-)2.+zI]VEQ:J"><mutation xmlns="http://www.w3.org/1999/xhtml" saved_name="x"/><field name="VAR" id="LF~^7y/5DU3P0YQE#o=}">inputField</field></block></value><value name="ADD1"><block type="text" id="u80UBaZHp~*r1?TJ)i2v"><field name="TEXT">Input</field></block></value></block></value></block></value></block></value><statement name="DO0"><block type="setter" id="Pd`A,K4o*s_ZWDE=IDRa"><mutation xmlns="http://www.w3.org/1999/xhtml" component_name="error_label(Profile)" parent_id="undefined"/><field name="component_id">c06550f1-e444-496b-b03f-e4ddbc3a4147</field><field name="field_name">Text</field><value name="field_value"><shadow type="text" id="MOd5Iok-;2CoO0u$(%KU"><field name="TEXT">Label</field></shadow><block type="text_join" id="=9M)ZfhX)[w6oKyt[=ZA"><mutation items="2"/><value name="ADD0"><block type="variables_get" id="LO$,~X6-J?NkZqfa|3L,"><mutation xmlns="http://www.w3.org/1999/xhtml" saved_name="x"/><field name="VAR" id="LF~^7y/5DU3P0YQE#o=}">inputField</field></block></value><value name="ADD1"><block type="text" id="CcJxh/wOVh-RHn)S~Ch)"><field name="TEXT"> field cannot be blank.</field></block></value></block></value><next><block type="variables_set" id="7~Ph951LsAI|SIDG=A3)"><mutation xmlns="http://www.w3.org/1999/xhtml" saved_name="app variable canMove"/><field name="VAR">24b66df5-ff5e-4123-b871-0e48b7557760</field><value name="VALUE"><block type="logic_boolean" id="ka!W3_8~o|ue]_f;fbnD"><field name="BOOL">FALSE</field></block></value></block></next></block></statement><statement name="ELSE"><block type="variables_set_dynamic" id="$B,qOf`7[=(w)qeQ:ff0"><field name="SCOPE">CLOUD</field><value name="NAME"><shadow type="text" id="//fc]!Q6D}.8dm*-JrCz"><field name="TEXT">name</field></shadow><block type="text_join" id="9$USamN)0SKAo:rU)utk"><mutation items="4"/><value name="ADD0"><block type="text" id="[Hm=VkLHirPA)@5Q=Tnc"><field name="TEXT">/users/</field></block></value><value name="ADD1"><block type="variables_get" id="j$d16)b{yx75z5;zKhkY"><mutation xmlns="http://www.w3.org/1999/xhtml" saved_name="app variable user ID"/><field name="VAR">5ba45984-1ac2-48dd-8711-47d78fbe1f24</field></block></value><value name="ADD2"><block type="text" id="f2uCQH.2!AoDb{Pg}SzB"><field name="TEXT">/</field></block></value><value name="ADD3"><block type="variables_get" id="+ZjhsWid+lS_wpDrCa7="><mutation xmlns="http://www.w3.org/1999/xhtml" saved_name="x"/><field name="VAR" id="LF~^7y/5DU3P0YQE#o=}">inputField</field></block></value></block></value><value name="VALUE"><block type="set_get" id="xXHcUE6J0WqdcPAf(iO3"><mutation xmlns="http://www.w3.org/1999/xhtml" component_block_input="true"/><field name="TYPE_component_id">Label</field><field name="field_name">Text</field><value name="component_id_SOCKET"><shadow type="any_component_component_dropdown" id="6ubO-pE34l~Dwa5L9PP`"><mutation xmlns="http://www.w3.org/1999/xhtml" component_id="error_label(Profile)" include_has_gettable_only="true"/><field name="component_id">c06550f1-e444-496b-b03f-e4ddbc3a4147</field></shadow><block type="text_join" id="SU_?.*9EPX[MIqcGbol#"><mutation items="2"/><value name="ADD0"><block type="variables_get" id="08My]|s{nhQRqsWLZsJ6"><mutation xmlns="http://www.w3.org/1999/xhtml" saved_name="x"/><field name="VAR" id="LF~^7y/5DU3P0YQE#o=}">inputField</field></block></value><value name="ADD1"><block type="text" id="-weOK=fLM?*0,#czJgL+"><field name="TEXT">Input</field></block></value></block></value></block></value></block></statement></block></statement></block><block type="component_event" id="/zOTwzb$Gk_Ft3b6yEpp" x="0" y="255"><mutation xmlns="http://www.w3.org/1999/xhtml" component_name="Profile" component_type="Screen" parent_id="undefined" event_id="Opens" was_updated="true"/><field name="component_id">08aa0a09-f8f4-4061-a426-b1b3a615b6a8</field><field name="event_id">Opens</field><statement name="input_do"><block type="controls_if" id="RS.hH/5`JhUK:XxH$I!R"><mutation else="1"/><value name="IF0"><block type="logic_compare" id="-I-SU%G@%9N*|xIyS_Z0"><field name="OP">EQ</field><value name="A"><block type="variables_get_dynamic" id="IoB^v`L$5AQz||)}Wl$m"><field name="SCOPE">CLOUD</field><value name="NAME"><shadow type="text" id="xNb``7C[Qh%r~P6yF%S5"><field name="TEXT">name</field></shadow><block type="text_join" id="=y8p(FcsF]0u-L^74@F|"><mutation items="2"/><value name="ADD0"><block type="text" id="yd@EucYDxjb0H^vzJGse"><field name="TEXT">/users/</field></block></value><value name="ADD1"><block type="variables_get" id="d,qH?Z=hYgPE#`--A,jB"><mutation xmlns="http://www.w3.org/1999/xhtml" saved_name="app variable user ID"/><field name="VAR">5ba45984-1ac2-48dd-8711-47d78fbe1f24</field></block></value></block></value></block></value><value name="B"><block type="logic_null" id="A*zM2d_U_eS-m(a(o]h-"/></value></block></value><statement name="DO0"><block type="variables_set_dynamic" id=".j{~4:9}{wPa@~UKs_1d"><field name="SCOPE">CLOUD</field><value name="NAME"><shadow type="text" id="+{`1M[6mz[B1.]DipFeq"><field name="TEXT">name</field></shadow><block type="variables_get" id="LH{tcK#)5$,XHF]^{DG*"><mutation xmlns="http://www.w3.org/1999/xhtml" saved_name="app variable user ID"/><field name="VAR">5ba45984-1ac2-48dd-8711-47d78fbe1f24</field></block></value><value name="VALUE"><block type="object_create" id="HtER!:]jx2b7WCM7Ks-u"><mutation xmlns="http://www.w3.org/1999/xhtml" num_fields="6"><field name=""/><field name=""/><field name=""/><field name=""/><field name=""/><field name=""/></mutation><field name="field1">fullName</field><field name="field2">university</field><field name="field3">majorsAndMinors</field><field name="field4">origin</field><field name="field5">about</field><field name="field6">image</field><value name="field_input1"><block type="logic_null" id="{.d|NNkU?H{|E:2puF?R"/></value><value name="field_input2"><block type="logic_null" id="bYSo^a[uySdGkxKmQGO,"/></value><value name="field_input3"><block type="logic_null" id="pt2l}ac?JQqga!YCurHq"/></value><value name="field_input4"><block type="logic_null" id="YfNy#H/gEvS/l$*]{QS5"/></value><value name="field_input5"><block type="logic_null" id="dYj-gvwrh9IPo$%gLT[!"/></value><value name="field_input6"><block type="logic_null" id="}Py`:%SD|.p6v[q.5/Qm"/></value></block></value></block></statement><statement name="ELSE"><block type="setter" id="Yfx{hISbQ305/Yr^:!Gb"><mutation xmlns="http://www.w3.org/1999/xhtml" component_name="fullNameInput" parent_id="undefined"/><field name="component_id">43d7ba8f-6357-4ebb-bdec-9026db0f6b41</field><field name="field_name">Text</field><value name="field_value"><shadow type="text" id="qZ~pR+R$SfGtQPK][s:j"><field name="TEXT"/></shadow><block type="variables_get_dynamic" id="qgk_Gtfn5eyH-HOTYj`9"><field name="SCOPE">CLOUD</field><value name="NAME"><shadow type="text" id="RICPjYG_xRSl/GTzTYt%"><field name="TEXT">name</field></shadow><block type="text_join" id="R~!0ZWZ^rbOedM%cwGm."><mutation items="3"/><value name="ADD0"><block type="text" id="dq)0f|4jBuV9#AB{u.t@"><field name="TEXT">/users/</field></block></value><value name="ADD1"><block type="variables_get" id="eypQuu$*g4:Rd=L~-:KI"><mutation xmlns="http://www.w3.org/1999/xhtml" saved_name="app variable user ID"/><field name="VAR">5ba45984-1ac2-48dd-8711-47d78fbe1f24</field></block></value><value name="ADD2"><block type="text" id="8Ba+:`p$l8Vntz!/+!~*"><field name="TEXT">/fullName</field></block></value></block></value></block></value><next><block type="setter" id="5gCPPZvhj0CX/$sQ4iEj"><mutation xmlns="http://www.w3.org/1999/xhtml" component_name="universityInput" parent_id="undefined"/><field name="component_id">422c19fe-8127-42f3-ac06-13acfcdb2c8f</field><field name="field_name">Text</field><value name="field_value"><shadow type="text" id="Z+U(xTkbBQW~LTaIN-,f"><field name="TEXT"/></shadow><block type="variables_get_dynamic" id="Z:rcVQ1PO)tZ1k][LHi%"><field name="SCOPE">CLOUD</field><value name="NAME"><shadow type="text" id="RICPjYG_xRSl/GTzTYt%"><field name="TEXT">name</field></shadow><block type="text_join" id="cxx^U+`_lZaht=v~QNv*"><mutation items="3"/><value name="ADD0"><block type="text" id="ID!6Yj,*OPUH@qTxUl=a"><field name="TEXT">/users/</field></block></value><value name="ADD1"><block type="variables_get" id="A:~r8G6*vVL`wayJ``|F"><mutation xmlns="http://www.w3.org/1999/xhtml" saved_name="app variable user ID"/><field name="VAR">5ba45984-1ac2-48dd-8711-47d78fbe1f24</field></block></value><value name="ADD2"><block type="text" id="=5buagzou6-Dx6sQaW.G"><field name="TEXT">/university</field></block></value></block></value></block></value><next><block type="setter" id="E4^6yfGQh_/:cPaHy^q)"><mutation xmlns="http://www.w3.org/1999/xhtml" component_name="majorsAndMinorsInput" parent_id="undefined"/><field name="component_id">48c412bc-2999-4fda-ae2e-86abec9433d8</field><field name="field_name">Text</field><value name="field_value"><shadow type="text" id="^Txrbysunja|JOrpgRlq"><field name="TEXT"/></shadow><block type="variables_get_dynamic" id="|OJ3GYno;d-sM[F}cIYm"><field name="SCOPE">CLOUD</field><value name="NAME"><shadow type="text" id="RICPjYG_xRSl/GTzTYt%"><field name="TEXT">name</field></shadow><block type="text_join" id="=yM0G^/qT!pe_18We1vR"><mutation items="3"/><value name="ADD0"><block type="text" id="C,kh;ectcaUk`baw~_P%"><field name="TEXT">/users/</field></block></value><value name="ADD1"><block type="variables_get" id="UBa5`A,hu!fXhsfWwXMf"><mutation xmlns="http://www.w3.org/1999/xhtml" saved_name="app variable user ID"/><field name="VAR">5ba45984-1ac2-48dd-8711-47d78fbe1f24</field></block></value><value name="ADD2"><block type="text" id=")pl2-`YvFszo+xCCowxV"><field name="TEXT">/majorsAndMinors</field></block></value></block></value></block></value><next><block type="setter" id="gI8EY-F~GUF^,#Tz*m8J"><mutation xmlns="http://www.w3.org/1999/xhtml" component_name="originInput" parent_id="undefined"/><field name="component_id">6865c7b4-824e-4520-8e5d-941adb605332</field><field name="field_name">Text</field><value name="field_value"><shadow type="text" id="8!-N~m|@Si,,~PPSYv;B"><field name="TEXT"/></shadow><block type="variables_get_dynamic" id="s%SO}:iLOuQE:]yiS}dU"><field name="SCOPE">CLOUD</field><value name="NAME"><shadow type="text" id="RICPjYG_xRSl/GTzTYt%"><field name="TEXT">name</field></shadow><block type="text_join" id=".PxE-7`6g0D)0HvPfbFB"><mutation items="3"/><value name="ADD0"><block type="text" id="%J7:x^!,nwkgHn{pwu1N"><field name="TEXT">/users/</field></block></value><value name="ADD1"><block type="variables_get" id="Q(@gZlk#n=NuFm|idIw="><mutation xmlns="http://www.w3.org/1999/xhtml" saved_name="app variable user ID"/><field name="VAR">5ba45984-1ac2-48dd-8711-47d78fbe1f24</field></block></value><value name="ADD2"><block type="text" id="hd)1K}yqCDDi!HB)jv@z"><field name="TEXT">/origin</field></block></value></block></value></block></value><next><block type="setter" id="da8hQDsi[~3[(YP2QK=;"><mutation xmlns="http://www.w3.org/1999/xhtml" component_name="aboutInput" parent_id="undefined"/><field name="component_id">f4cb56f9-b82c-4169-af36-f3b078a48ff5</field><field name="field_name">Text</field><value name="field_value"><shadow type="text" id="k0Mht6DD*FxGx[f6ZY,k"><field name="TEXT"/></shadow><block type="variables_get_dynamic" id="2y=+Z=vxexjt-lCq;4Na"><field name="SCOPE">CLOUD</field><value name="NAME"><shadow type="text" id="RICPjYG_xRSl/GTzTYt%"><field name="TEXT">name</field></shadow><block type="text_join" id="`sPVRQOWY@}lQP/)UMt."><mutation items="3"/><value name="ADD0"><block type="text" id="r+NQ,/L[wE9N/X(S?~$R"><field name="TEXT">/users/</field></block></value><value name="ADD1"><block type="variables_get" id="*LeUnpPO6_=r6YkgMs9P"><mutation xmlns="http://www.w3.org/1999/xhtml" saved_name="app variable user ID"/><field name="VAR">5ba45984-1ac2-48dd-8711-47d78fbe1f24</field></block></value><value name="ADD2"><block type="text" id="^CZ?o|:M$FW@:8xc@:gp"><field name="TEXT">/about</field></block></value></block></value></block></value><next><block type="setter" id="X%;YC{{Jc9u1?-5U4UZ/"><mutation xmlns="http://www.w3.org/1999/xhtml" component_name="profileImage" parent_id="undefined"/><field name="component_id">28d6c084-9071-4368-a643-1eaedfa86823</field><field name="field_name">Picture</field><value name="field_value"><shadow type="asset_get" id="ar/~EDG(_$y4462qbZdA"><mutation xmlns="http://www.w3.org/1999/xhtml" previous_asset_name="Logo (3).png" previous_asset_value="6535bd46d0ee6a0f6ab3bad2"/><field name="ASSET">6535bd46d0ee6a0f6ab3bad2</field></shadow><block type="variables_get_dynamic" id="VUXLVw;WHtnc~n34%pNV"><field name="SCOPE">CLOUD</field><value name="NAME"><shadow type="text" id="RICPjYG_xRSl/GTzTYt%"><field name="TEXT">name</field></shadow><block type="text_join" id="N1E_4mT{?G7K1[MT:z9w"><mutation items="3"/><value name="ADD0"><block type="text" id="AIgf6.pd1n??|?i?4KV|"><field name="TEXT">/users/</field></block></value><value name="ADD1"><block type="variables_get" id="c=(Zw==SJ{Dvd%py]g:p"><mutation xmlns="http://www.w3.org/1999/xhtml" saved_name="app variable user ID"/><field name="VAR">5ba45984-1ac2-48dd-8711-47d78fbe1f24</field></block></value><value name="ADD2"><block type="text" id="?~p$Bg0L^yel7h=rlgm("><field name="TEXT">/image</field></block></value></block></value></block></value></block></next></block></next></block></next></block></next></block></next></block></statement></block></statement></block><block type="component_event" id="q?ebmlYtHnqcqxr;4qM+" x="3" y="1143"><mutation xmlns="http://www.w3.org/1999/xhtml" component_name="saveInfoButton" component_type="Button" parent_id="undefined" event_id="Click" was_updated="true"/><field name="component_id">92235f90-e108-43ca-9369-572c69bed621</field><field name="event_id">Click</field><comment pinned="false" h="63" w="546">When saveInfoButton is clicked, call the updateUserData for every field. If there is no empty field, navigate to Home</comment><statement name="input_do"><block type="setter" id="xo@HUnz?Vo:v6]q@:d;^"><mutation xmlns="http://www.w3.org/1999/xhtml" component_name="error_label(Profile)" parent_id="undefined"/><field name="component_id">c06550f1-e444-496b-b03f-e4ddbc3a4147</field><field name="field_name">Text</field><value name="field_value"><shadow type="text" id="MOd5Iok-;2CoO0u$(%KU"><field name="TEXT"/></shadow></value><next><block type="variables_set" id="!R^=@3IY^AI0#;JS`$$2"><mutation xmlns="http://www.w3.org/1999/xhtml" saved_name="app variable canMove"/><field name="VAR">24b66df5-ff5e-4123-b871-0e48b7557760</field><value name="VALUE"><block type="logic_boolean" id="1wz.,VX0}zt-B5CzFx.+"><field name="BOOL">TRUE</field></block></value><next><block type="procedures_callnoreturn" id="8MI$E/K5Fgf-JkmO7;ro"><mutation name="updateUserData"><arg name="inputField"/></mutation><value name="ARG0"><block type="text" id=";xGs(l=SIz#U1?0$9w=]"><field name="TEXT">fullName</field></block></value><next><block type="procedures_callnoreturn" id="4_,`:t5f1,H8K|H+o`qZ"><mutation name="updateUserData"><arg name="inputField"/></mutation><value name="ARG0"><block type="text" id="%?7,wri_/3Q^FD8-e}:l"><field name="TEXT">university</field></block></value><next><block type="procedures_callnoreturn" id="swLGRw)@8cw6c-)+50^f"><mutation name="updateUserData"><arg name="inputField"/></mutation><value name="ARG0"><block type="text" id="5{*2;gySM$A?U-iiWDKL"><field name="TEXT">majorsAndMinors</field></block></value><next><block type="procedures_callnoreturn" id="^Q9Xi5y/%zy|1EuP:nmS"><mutation name="updateUserData"><arg name="inputField"/></mutation><value name="ARG0"><block type="text" id="M2`P~40%W9Wh](s1T/Wx"><field name="TEXT">origin</field></block></value><next><block type="procedures_callnoreturn" id="rx/5HN%pv,I#2t25E2T4"><mutation name="updateUserData"><arg name="inputField"/></mutation><value name="ARG0"><block type="text" id="tVq0=X5LSgM8RQ_KCXgb"><field name="TEXT">about</field></block></value><next><block type="controls_if" id="E!rhUZRdrj*Jji_1X)PB"><value name="IF0"><block type="logic_compare" id="szzGZ6@)RFg|L|YZ,2|K"><field name="OP">EQ</field><value name="A"><block type="variables_get" id="3A5K=i@=,jtoJdY.UYsO"><mutation xmlns="http://www.w3.org/1999/xhtml" saved_name="app variable canMove"/><field name="VAR">24b66df5-ff5e-4123-b871-0e48b7557760</field></block></value><value name="B"><block type="logic_boolean" id="Ht++VyuJ(mqw((hW*,!V"><field name="BOOL">TRUE</field></block></value></block></value><statement name="DO0"><block type="controls_navigate_new" id="cG-TG)EifxTOq-{?RZ:-"><value name="COMPONENT"><shadow type="any_component_component_dropdown" id=".;t{F12/L0xU+{h*QbmO"><mutation xmlns="http://www.w3.org/1999/xhtml" component_id="Home" component_types_to_include="[&quot;Screen&quot;]"/><field name="component_id">566a014c-221f-4c25-901b-76a6636ebadc</field></shadow></value></block></statement></block></next></block></next></block></next></block></next></block></next></block></next></block></next></block></statement></block><block type="component_event" id="Aw0GdeCt}r5X`gA.;3|s" x="2" y="1626"><mutation xmlns="http://www.w3.org/1999/xhtml" component_name="uploadProfileImageButton" component_type="Button" parent_id="undefined" event_id="Click" was_updated="true"/><field name="component_id">eb1b563d-14aa-44fb-ae6d-5075d5ee2917</field><field name="event_id">Click</field><statement name="input_do"><block type="camera_select_photo_advanced" id="K6^dPOPI/u`^#I96qulV" inline="false"><mutation xmlns="http://www.w3.org/1999/xhtml" show_callback_params="true" callback_params_added="true"/><field name="MEDIA_TYPE_OPTIONS">PHOTO</field><value name="CALLBACK_PARAM0"><block type="callback_arg" id="]{J5*2ZYDj270PdFpLZ7"><mutation xmlns="http://www.w3.org/1999/xhtml" tooltip="" language_neutral_name="photo" arg_name_trans_key="blocks.camera.select_photo.photo_or_video" old_arg_name="photo or video"/></block></value><value name="CALLBACK_PARAM1"><block type="callback_arg" id="Y5n/9d)c{E[kX0wa/D`-"><mutation xmlns="http://www.w3.org/1999/xhtml" tooltip="" language_neutral_name="cancel" arg_name_trans_key="blocks.camera.select_photo.cancel" old_arg_name="was cancelled"/></block></value><value name="CALLBACK_PARAM2"><block type="callback_arg" id="+%K7RSmfX29-C4@6U:Mx"><mutation xmlns="http://www.w3.org/1999/xhtml" tooltip="" language_neutral_name="error" arg_name_trans_key="blocks.camera.error" old_arg_name="error"/></block></value><statement name="DO"><block type="controls_if" id="1+I|`3XXmARDY4RW%vz/"><value name="IF0"><block type="logic_negate" id="U6+5?t_2Hn~4mn(Q2aRa"><value name="BOOL"><block type="callback_arg" id="Fjuf:$G_PB73R|vsa]P|"><mutation xmlns="http://www.w3.org/1999/xhtml" tooltip="" language_neutral_name="cancel" arg_name_trans_key="blocks.camera.select_photo.cancel" old_arg_name="was cancelled" is_detached_parameter="true"/></block></value></block></value><statement name="DO0"><block type="controls_if" id="YpyAYga0[X),:QYk-p-x"><mutation else="1"/><value name="IF0"><block type="callback_arg" id="]S:gV4~er#o!SalKijy$"><mutation xmlns="http://www.w3.org/1999/xhtml" tooltip="" language_neutral_name="error" arg_name_trans_key="blocks.camera.error" old_arg_name="error" is_detached_parameter="true"/></block></value><statement name="DO0"><block type="setter" id="V9*wcF+h{y*~0UzD`:_0"><mutation xmlns="http://www.w3.org/1999/xhtml" component_name="error_label(Profile)" parent_id="undefined"/><field name="component_id">c06550f1-e444-496b-b03f-e4ddbc3a4147</field><field name="field_name">Text</field><value name="field_value"><shadow type="text" id="_j}!7xgK[CDixBs~Vp$e"><field name="TEXT">Label</field></shadow><block type="callback_arg" id="dxx:Mine2)I@G,?OUCk]"><mutation xmlns="http://www.w3.org/1999/xhtml" tooltip="" language_neutral_name="error" arg_name_trans_key="blocks.camera.error" old_arg_name="error" is_detached_parameter="true"/></block></value></block></statement><statement name="ELSE"><block type="camera_upload_image_advanced" id="JkmYR|d;$w|3k}fGR]W7" inline="false"><mutation xmlns="http://www.w3.org/1999/xhtml" show_callback_params="true" callback_params_added="true"/><value name="IMAGE"><shadow type="asset_get" id="o0TcMB=Ou!=J8)m_969|"><mutation xmlns="http://www.w3.org/1999/xhtml" previous_asset_name="Logo (3).png" previous_asset_value="6535bd46d0ee6a0f6ab3bad2"/><field name="ASSET">6535bd46d0ee6a0f6ab3bad2</field></shadow><block type="callback_arg" id="c~1V{J$FLx(,qByomAl)"><mutation xmlns="http://www.w3.org/1999/xhtml" tooltip="" language_neutral_name="photo" arg_name_trans_key="blocks.camera.select_photo.photo_or_video" old_arg_name="photo or video"/></block></value><value name="CALLBACK_PARAM0"><block type="callback_arg" id="%5K+PW*wEpW;,5#{JnaI"><mutation xmlns="http://www.w3.org/1999/xhtml" tooltip="" language_neutral_name="url" arg_name_trans_key="blocks.camera.upload_image.url" old_arg_name="url"/></block></value><value name="CALLBACK_PARAM1"><block type="callback_arg" id=".}5sHDEs^E8q44?Xtr(A"><mutation xmlns="http://www.w3.org/1999/xhtml" tooltip="" language_neutral_name="error" arg_name_trans_key="blocks.sound.error" old_arg_name="error"/></block></value><statement name="DO"><block type="controls_if" id="A}vG`#5}N8|dcsk(o.+8"><mutation else="1"/><value name="IF0"><block type="callback_arg" id="JGd)#`MLh(Z$fqfm}9=B"><mutation xmlns="http://www.w3.org/1999/xhtml" tooltip="" language_neutral_name="error" arg_name_trans_key="blocks.sound.error" old_arg_name="error" is_detached_parameter="true"/></block></value><statement name="DO0"><block type="setter" id="S1`7Nz@IK.5bEo-ov=B1"><mutation xmlns="http://www.w3.org/1999/xhtml" component_name="error_label(Profile)" parent_id="undefined"/><field name="component_id">c06550f1-e444-496b-b03f-e4ddbc3a4147</field><field name="field_name">Text</field><value name="field_value"><shadow type="text" id="c}[.4/8tf%mPyhpzMmZK"><field name="TEXT">Label</field></shadow><block type="callback_arg" id="w.l,U^UE6d%e*{j1|}8S"><mutation xmlns="http://www.w3.org/1999/xhtml" tooltip="" language_neutral_name="error" arg_name_trans_key="blocks.camera.error" old_arg_name="error" is_detached_parameter="true"/></block></value></block></statement><statement name="ELSE"><block type="variables_set_dynamic" id="7Q2b=@DTYQlfiR31tY!V"><field name="SCOPE">CLOUD</field><value name="NAME"><shadow type="text" id="p[Ci8G|U):du4#:ofup$"><field name="TEXT">name</field></shadow><block type="text_join" id=")Q14+8TXo{3`bKW~w+.{"><mutation items="3"/><value name="ADD0"><block type="text" id="56e}qdNZiuP2FKByuZ)y"><field name="TEXT">/users/</field></block></value><value name="ADD1"><block type="variables_get" id="/|IaVb`!3P(K[/J@=(N?"><mutation xmlns="http://www.w3.org/1999/xhtml" saved_name="app variable user ID"/><field name="VAR">5ba45984-1ac2-48dd-8711-47d78fbe1f24</field></block></value><value name="ADD2"><block type="text" id="0n5}}LFCC+JNFe)m^m6P"><field name="TEXT">/image</field></block></value></block></value><value name="VALUE"><block type="callback_arg" id="k|E[x!2FK#A8)8~{AyE,"><mutation xmlns="http://www.w3.org/1999/xhtml" tooltip="" language_neutral_name="url" arg_name_trans_key="blocks.camera.upload_image.url" old_arg_name="url" is_detached_parameter="true"/></block></value><next><block type="setter" id="@yInqDi^8?q:~;{=ES=6"><mutation xmlns="http://www.w3.org/1999/xhtml" component_name="profileImage" parent_id="undefined"/><field name="component_id">28d6c084-9071-4368-a643-1eaedfa86823</field><field name="field_name">Picture</field><value name="field_value"><shadow type="asset_get" id="O5PQ_3A/fI74yi~PX/9W"><mutation xmlns="http://www.w3.org/1999/xhtml" previous_asset_name="Logo (3).png" previous_asset_value="6535bd46d0ee6a0f6ab3bad2"/><field name="ASSET">6535bd46d0ee6a0f6ab3bad2</field></shadow><block type="variables_get_dynamic" id="v8I]+hK6#BI~MsSsN,W7"><field name="SCOPE">CLOUD</field><value name="NAME"><shadow type="text" id=")Z|v?KS~*EJyI6ksXhp("><field name="TEXT">name</field></shadow><block type="text_join" id="1WRx]);BN%,UFAJ|sv0q"><mutation items="3"/><value name="ADD0"><block type="text" id="dPgkHP2LiZ8g:#iY,?F:"><field name="TEXT">/users/</field></block></value><value name="ADD1"><block type="variables_get" id="{#CQnME.Ks:d})DUfquV"><mutation xmlns="http://www.w3.org/1999/xhtml" saved_name="app variable user ID"/><field name="VAR">5ba45984-1ac2-48dd-8711-47d78fbe1f24</field></block></value><value name="ADD2"><block type="text" id="LeRXF8k+]W=R%cS:o)`t"><field name="TEXT">/image</field></block></value></block></value></block></value></block></next></block></statement></block></statement></block></statement></block></statement></block></statement></block></statement></block></xml>